guidepost/__init__.py
guidepost/guidepost.js
guidepost/guidepost.py
guidepost/version.py
guidepost-0.2.18.dist-info/licenses/LICENSE
tutorials/__init__.py
guidepost-0.2.18.dist-info/METADATA
guidepost-0.2.18.dist-info/WHEEL
guidepost-0.2.18.dist-info/top_level.txt
guidepost-0.2.18.dist-info/RECORD
