Metadata-Version: 2.4
Name: guidepost
Version: 0.2.18
Summary: Guidepost. An overview visualization for understanding supercomputer queue data.
Home-page: https://github.com/cscully-allison/guidepost
Author: Connor Scully-Allison
Author-email: cscullyallison@sci.utah.edu
Classifier: Programming Language :: Python :: 3
Classifier: License :: OSI Approved :: MIT License
Classifier: Operating System :: OS Independent
Requires-Python: >=3.6
License-File: LICENSE
Requires-Dist: numpy
Requires-Dist: pandas
Requires-Dist: scikit-learn
Requires-Dist: anywidget
Requires-Dist: traitlets
Dynamic: author
Dynamic: author-email
Dynamic: classifier
Dynamic: description
Dynamic: description-content-type
Dynamic: home-page
Dynamic: license-file
Dynamic: requires-dist
Dynamic: requires-python
Dynamic: summary
